<?xml version="1.0" encoding="UTF-8"?>
<xml>
  <file>
    <title>DefStripSize</title>
    <breadcumbs>
      <link file="TiffCodec.xml">
        <text>TiffCodec</text>
      </link>
    </breadcumbs>
    <descriptionarticle only="false" />
    <signature>
      <function>
        <mod2>virtual</mod2>
        <name>DefStripSize</name>
        <return type="Int32" />
        <parameters>
          <parameter name="s" type="Int32" />
        </parameters>
      </function>
    </signature>
  </file>
</xml>